quantrading/__init__.py
quantrading/performance_utils.py
quantrading/time_series_utils.py
quantrading/utils.py
quantrading/backtest/__init__.py
quantrading/backtest/backtest.py
quantrading/backtest/backtest_base.py
quantrading/backtest/backtest_open_close.py
quantrading/backtest/light_backtest.py
quantrading/backtest/portfolio.py
quantrading/backtest/simulation_result_utils.py
quantrading/backtest/trading_day.py
quantrading/backtest/utils.py
quantrading/simulation/__init__.py
quantrading/simulation/monte_carlo.py
quantrading-0.1.41.dist-info/METADATA
quantrading-0.1.41.dist-info/WHEEL
quantrading-0.1.41.dist-info/top_level.txt
quantrading-0.1.41.dist-info/RECORD
