Metadata-Version: 2.1
Name: quantrading
Version: 0.1.41
Summary: backtest utils
Home-page: https://github.com/quantrading/quantrading
Author: Jang Woo Jae
Author-email: dnwogo@naver.com
License: MIT
Platform: UNKNOWN
Requires-Python: >=3
Requires-Dist: empyrical
Requires-Dist: openpyxl
Requires-Dist: xlsxwriter
Requires-Dist: plotly
